adgtk/__init__.py
adgtk/clean.tar
adgtk/defaults.py
adgtk/template.tar
adgtk/.mypy_cache/.gitignore
adgtk/.mypy_cache/CACHEDIR.TAG
adgtk/.mypy_cache/3.10/@plugins_snapshot.json
adgtk/.mypy_cache/3.10/_ast.data.json
adgtk/.mypy_cache/3.10/_ast.meta.json
adgtk/.mypy_cache/3.10/_codecs.data.json
adgtk/.mypy_cache/3.10/_codecs.meta.json
adgtk/.mypy_cache/3.10/_collections_abc.data.json
adgtk/.mypy_cache/3.10/_collections_abc.meta.json
adgtk/.mypy_cache/3.10/abc.data.json
adgtk/.mypy_cache/3.10/abc.meta.json
adgtk/.mypy_cache/3.10/builtins.data.json
adgtk/.mypy_cache/3.10/builtins.meta.json
adgtk/.mypy_cache/3.10/check_venv.data.json
adgtk/.mypy_cache/3.10/check_venv.meta.json
adgtk/.mypy_cache/3.10/codecs.data.json
adgtk/.mypy_cache/3.10/codecs.meta.json
adgtk/.mypy_cache/3.10/contextlib.data.json
adgtk/.mypy_cache/3.10/contextlib.meta.json
adgtk/.mypy_cache/3.10/dataclasses.data.json
adgtk/.mypy_cache/3.10/dataclasses.meta.json
adgtk/.mypy_cache/3.10/enum.data.json
adgtk/.mypy_cache/3.10/enum.meta.json
adgtk/.mypy_cache/3.10/genericpath.data.json
adgtk/.mypy_cache/3.10/genericpath.meta.json
adgtk/.mypy_cache/3.10/io.data.json
adgtk/.mypy_cache/3.10/io.meta.json
adgtk/.mypy_cache/3.10/pathlib.data.json
adgtk/.mypy_cache/3.10/pathlib.meta.json
adgtk/.mypy_cache/3.10/posixpath.data.json
adgtk/.mypy_cache/3.10/posixpath.meta.json
adgtk/.mypy_cache/3.10/re.data.json
adgtk/.mypy_cache/3.10/re.meta.json
adgtk/.mypy_cache/3.10/resource.data.json
adgtk/.mypy_cache/3.10/resource.meta.json
adgtk/.mypy_cache/3.10/sre_compile.data.json
adgtk/.mypy_cache/3.10/sre_compile.meta.json
adgtk/.mypy_cache/3.10/sre_constants.data.json
adgtk/.mypy_cache/3.10/sre_constants.meta.json
adgtk/.mypy_cache/3.10/sre_parse.data.json
adgtk/.mypy_cache/3.10/sre_parse.meta.json
adgtk/.mypy_cache/3.10/subprocess.data.json
adgtk/.mypy_cache/3.10/subprocess.meta.json
adgtk/.mypy_cache/3.10/types.data.json
adgtk/.mypy_cache/3.10/types.meta.json
adgtk/.mypy_cache/3.10/typing.data.json
adgtk-0.1.3.dist-info/licenses/LICENSE
adgtk-0.1.3.dist-info/METADATA
adgtk-0.1.3.dist-info/WHEEL
adgtk-0.1.3.dist-info/entry_points.txt
adgtk-0.1.3.dist-info/top_level.txt
adgtk-0.1.3.dist-info/RECORD
