Metadata-Version: 2.4
Name: adgtk
Version: 0.1.3
Summary: A framework for researching automation of synthetic data generation.
Author-email: Frederick Diehl <fdiehl@ualr.edu>
Project-URL: Homepage, https://github.com/fred78108/adgtk
Project-URL: Documentation, https://adgtk.readthedocs.io/en/latest/
Project-URL: Issues, https://github.com/fred78108/adgtk/issues
Classifier: Development Status :: 3 - Alpha
Classifier: Programming Language :: Python :: 3
Classifier: License :: OSI Approved :: MIT License
Classifier: Operating System :: OS Independent
Requires-Python: >=3.12
License-File: LICENSE
Requires-Dist: toml
Requires-Dist: jinja2
Requires-Dist: PyYAML
Requires-Dist: regex
Requires-Dist: requests
Requires-Dist: anytree
Requires-Dist: matplotlib
Requires-Dist: prompt_toolkit
Dynamic: license-file
